<?xml version="1.0" encoding="utf-8"?>
<extensionAdditionalInfo>
  <info><![CDATA[
    <p>
	  This extension contains actions for working with ComponentOne's
	  Doc-To-Help.
	</p>
  ]]></info>
  <actionInfo id="Inedo.BuildMasterExtensions.DocToHelp.BuildProject" name="Build Doc-To-Help Project" summary="Builds a Doc-To-Help project."><![CDATA[
    <p>
	  Builds a Doc-To-Help project.
	</p>
	<h3>Action Fields</h3>
	<h4>Project File</h4>
	<p>
	  The Doc-To-Help project file (.d2h) to build. This may be a path
	  relative to the source directory or an absolute path. Note that the
	  output directory is specified in the project and is generally also
	  relative to the source directory.
	</p>
	<h4>Help Target</h4>
	<p>
	  The name of the Doc-To-Help target to build. This should be the exact
	  name of the help target as specified in the project. For example, NetHelp
	  or HTMLHelp.
	</p>
  ]]></actionInfo>
</extensionAdditionalInfo>